reddit_rss_reader/__init__.py
reddit_rss_reader/reader.py
reddit_rss_reader-1.3.2.dist-info/LICENSE
reddit_rss_reader-1.3.2.dist-info/METADATA
reddit_rss_reader-1.3.2.dist-info/WHEEL
reddit_rss_reader-1.3.2.dist-info/top_level.txt
reddit_rss_reader-1.3.2.dist-info/RECORD
