Metadata-Version: 2.1
Name: reddit-rss-reader
Version: 1.3.2
Summary: A Wrapper around Reddit RSS feed
Home-page: https://github.com/lalitpagaria/reddit-rss-reader
Author: Lalit Pagaria
Author-email: pagaria.lalit@gmail.com
License: Apache Version 2.0
Platform: UNKNOWN
Classifier: Development Status :: 5 - Production/Stable
Classifier: Intended Audience :: Developers
Classifier: Intended Audience :: Customer Service
Classifier: Intended Audience :: Information Technology
Classifier: License :: OSI Approved :: Apache Software License
Classifier: Operating System :: OS Independent
Classifier: Programming Language :: Python :: 3.6
Classifier: Programming Language :: Python :: 3.7
Classifier: Programming Language :: Python :: 3.8
Classifier: Programming Language :: Python :: 3.9
Classifier: Topic :: Software Development :: Libraries :: Python Modules
Requires-Python: >=3.6.0
Requires-Dist: feedparser
Requires-Dist: beautifulsoup4
Requires-Dist: requests
